Workbook
Name p3341_48900: '2026'!$F$1427
Name p2311_48900: '2026'!$F$1405
Name p4320_46700: '2026'!$F$1448
Name p3260_48900: '2026'!$F$1415
Name p1610_48900: '2026'!$F$1393
Name suma_cap5: '2026'!$F$1483
Name suma_cap9: '2026'!$F$1717
Name suma_cap2: '2026'!$F$1371
Name p3380_48900: '2026'!$F$1435
Name suma_cap4: '2026'!$F$1473
Name p9430_48900: '2026'!$F$1470
Name p3262_48900: '2026'!$F$1419
Name p9240_48900: '2026'!$F$1466
Name p2311_48901: '2026'!$F$1406
Name p4330_47900: '2026'!$F$1453
Name suma_cap1: '2026'!$F$508
Name p4320_48900: '2026'!$F$1449
Name P3360_78000: '2026'!$F$1694
Name p1700_48900: '2026'!$F$1397
Name p4310_48900: '2026'!$F$1444
Name suma_cap3: '2026'!$F$1386
Name suma_cap6: '2026'!$F$1682
Name p9200_48900: '2026'!$F$1462
Name p3340_48900: '2026'!$F$1423
Name p1710_48900: '2026'!$F$1401
Name p1522_78000: '2026'!$F$1689
Name suma_cap8: '2026'!$F$1707
Name p1522_78001: '2026'!$F$1690
Name p2313_48900: '2026'!$F$1411
Name p3373_48900: '2026'!$F$1431
Name p3410_48900: '2026'!$F$1439
Name p2311_48902: '2026'!$F$1407
Name p4330_48900: '2026'!$F$1454
Name suma_cap7: '2026'!$F$1697
Name p9120_48900: '2026'!$F$1458

Sheet 2026
G1: =IFERROR(((E1-#REF!)/#REF!), "")
G2: =IFERROR(((E2-#REF!)/#REF!), "")
B3: CLASIFICACIÓN | D3: CAPÍTULO I | G3: =IFERROR(((E3-#REF!)/#REF!), "")
B4: PROGRAMA | C4: ECONÓMICA | G4: =IFERROR(((E4-#REF!)/#REF!), "")
B5: 1300 | D5: ADMON. GRAL. DE LA SEGURIDAD | E5: 2025 | F5: 2026 | G5: =IFERROR(((F5-E5)/E5), "") -> 0.00049382716
C6: 120.03 | D6: Sueldos del Grupo C1 | E6: 29000 | F6: 29000 | G6: =IFERROR(((F6-E6)/E6), "") -> 0
C7: 120.04 | D7: Sueldos del Grupo C2 | E7: 25000 | F7: 25000 | G7: =IFERROR(((F7-E7)/E7), "") -> 0
C8: 120.06 | D8: Trienios | E8: 6775 | F8: 6775 | G8: =IFERROR(((F8-E8)/E8), "") -> 0
C9: 121.00 | D9: Complemento de destino | E9: 21150 | F9: 21150 | G9: =IFERROR(((F9-E9)/E9), "") -> 0
C10: 121.01 | D10: Complemento específico | E10: 28150 | F10: 28150 | G10: =IFERROR(((F10-E10)/E10), "") -> 0
C11: 150 | D11: Productividad | E11: 2800 | F11: 2800 | G11: =IFERROR(((F11-E11)/E11), "") -> 0
C12: 160.00 | D12: Cuotas Seguridad Social | E12: 33500 | F12: 33500 | G12: =IFERROR(((F12-E12)/E12), "") -> 0
C13: 131.00 | D13: Retribuciones básicas | E13: 18500 | F13: 18500 | G13: =IFERROR(((F13-E13)/E13), "") -> 0
C14: 131.02 | D14: Otras remuneraciones | E14: 5500 | F14: 5500 | G14: =IFERROR(((F14-E14)/E14), "") -> 0
C15: 160.02 | D15: Cuotas Seguridad Social | E15: 6800 | F15: 6800 | G15: =IFERROR(((F15-E15)/E15), "") -> 0
D16: 1300 | E16: 177175 | F16: =SUM(F6:F15) -> 177175 | G16: =IFERROR(((F16-E16)/E16), "") -> 0
G17: =IFERROR(((F17-E17)/E17), "")
B18: 1320 | D18: SEGURIDAD | E18: 2025 | F18: 2026 | G18: =IFERROR(((F18-E18)/E18), "") -> 0.00049382716
C19: 120.01 | D19: Sueldos del Grupo A2 | E19: 20100 | F19: 20100 | G19: =IFERROR(((F19-E19)/E19), "") -> 0
C20: 120.03 | D20: Sueldos del Grupo C1 | E20: 701000 | F20: 701000 | G20: =IFERROR(((F20-E20)/E20), "") -> 0
C21: 120.06 | D21: Trienios | E21: 55500 | F21: 55500 | G21: =IFERROR(((F21-E21)/E21), "") -> 0
C22: 121.00 | D22: Complemento de destino | E22: 232000 | F22: 232000 | G22: =IFERROR(((F22-E22)/E22), "") -> 0
C23: 121.01 | D23: Complemento específico | E23: 446000 | F23: 446000 | G23: =IFERROR(((F23-E23)/E23), "") -> 0
C24: 150 | D24: Productividad | E24: 132000 | F24: 132000 | G24: =IFERROR(((F24-E24)/E24), "") -> 0
C25: 151.00 | D25: Gratificaciones | E25: 310000 | F25: 310000 | G25: =IFERROR(((F25-E25)/E25), "") -> 0
C26: 160.00 | D26: Cuotas Seguridad Social | E26: 598000 | F26: 598000 | G26: =IFERROR(((F26-E26)/E26), "") -> 0
D27: 1320 | E27: 2494600 | F27: =SUM(F19:F26) -> 2494600 | G27: =IFERROR(((F27-E27)/E27), "") -> 0
G28: =IFERROR(((F28-E28)/E28), "")
B29: 1360 | D29: EXTINCIÓN DE INCENDIOS | E29: 2025 | F29: 2026 | G29: =IFERROR(((F29-E29)/E29), "") -> 0.00049382716
C30: 120.00 | D30: Sueldos del Grupo A1 | E30: 21500 | F30: 21500 | G30: =IFERROR(((F30-E30)/E30), "") -> 0
C31: 120.01 | D31: Sueldos del Grupo A2 | E31: 0 | F31: 0 | G31: =IFERROR(((F31-E31)/E31), "")
C32: 120.03 | D32: Sueldos del Grupo C1 | E32: 341000 | F32: 341000 | G32: =IFERROR(((F32-E32)/E32), "") -> 0
C33: 120.04 | D33: Sueldos del Grupo C2 | E33: 0 | F33: 0 | G33: =IFERROR(((F33-E33)/E33), "")
C34: 120.06 | D34: Trienios | E34: 68000 | F34: 68000 | G34: =IFERROR(((F34-E34)/E34), "") -> 0
C35: 121.00 | D35: Complemento de destino | E35: 155000 | F35: 155000 | G35: =IFERROR(((F35-E35)/E35), "") -> 0
C36: 121.01 | D36: Complemento específico | E36: 256000 | F36: 256000 | G36: =IFERROR(((F36-E36)/E36), "") -> 0
C37: 150 | D37: Productividad | E37: 400000 | F37: 400000 | G37: =IFERROR(((F37-E37)/E37), "") -> 0
C38: 151.00 | D38: Gratificaciones | E38: 300000 | F38: 300000 | G38: =IFERROR(((F38-E38)/E38), "") -> 0
C39: 160.00 | D39: Cuotas Seguridad Social | E39: 386000 | F39: 386000 | G39: =IFERROR(((F39-E39)/E39), "") -> 0
B40: 1360 | E40: 1927500 | F40: =SUM(F30:F39) -> 1927500 | G40: =IFERROR(((F40-E40)/E40), "") -> 0
G41: =IFERROR(((F41-E41)/E41), "")
B42: 1500 | D42: ADMON. GRAL. DE URBANISMO | E42: 2025 | F42: 2026 | G42: =IFERROR(((F42-E42)/E42), "") -> 0.00049382716
C43: 120.03 | D43: Sueldos del Grupo C1 | E43: 15000 | F43: 15000 | G43: =IFERROR(((F43-E43)/E43), "") -> 0
C44: 120.04 | D44: Sueldos del Grupo C2 | E44: 38000 | F44: 38000 | G44: =IFERROR(((F44-E44)/E44), "") -> 0
C45: 120.06 | D45: Trienios | E45: 7000 | F45: 7000 | G45: =IFERROR(((F45-E45)/E45), "") -> 0
C46: 121.00 | D46: Complemento de destino | E46: 22000 | F46: 22000 | G46: =IFERROR(((F46-E46)/E46), "") -> 0
C47: 121.01 | D47: Complemento específico | E47: 36000 | F47: 36000 | G47: =IFERROR(((F47-E47)/E47), "") -> 0
C48: 150 | D48: Productividad | E48: 2700 | F48: 2700 | G48: =IFERROR(((F48-E48)/E48), "") -> 0
C49: 160.00 | D49: Cuotas Seguridad Social | E49: 32500 | F49: 32500 | G49: =IFERROR(((F49-E49)/E49), "") -> 0
B50: 1500 | E50: 153200 | F50: =SUM(F43:F49) -> 153200 | G50: =IFERROR(((F50-E50)/E50), "") -> 0
G51: =IFERROR(((F51-E51)/E51), "")
B52: 1510 | D52: URBANISMO | E52: 2025 | F52: 2026 | G52: =IFERROR(((F52-E52)/E52), "") -> 0.00049382716
C53: 120.00 | D53: Sueldos del Grupo A1 | E53: 121600 | F53: 121600 | G53: =IFERROR(((F53-E53)/E53), "") -> 0
C54: 120.01 | D54: Sueldos del Grupo A2 | E54: 18600 | F54: 18600 | G54: =IFERROR(((F54-E54)/E54), "") -> 0
C55: 120.06 | D55: Trienios | E55: 18000 | F55: 18000 | G55: =IFERROR(((F55-E55)/E55), "") -> 0
C56: 121.00 | D56: Complemento de destino | E56: 29900 | F56: 29900 | G56: =IFERROR(((F56-E56)/E56), "") -> 0
C57: 121.01 | D57: Complemento específico | E57: 93000 | F57: 93000 | G57: =IFERROR(((F57-E57)/E57), "") -> 0
C58: 150 | D58: Productividad | E58: 5800 | F58: 5800 | G58: =IFERROR(((F58-E58)/E58), "") -> 0
C59: 160.00 | D59: Cuotas Seguridad Social | E59: 86000 | F59: 86000 | G59: =IFERROR(((F59-E59)/E59), "") -> 0
C60: 131.00 | D60: Retribuciones básicas | E60: 122000 | F60: 122000 | G60: =IFERROR(((F60-E60)/E60), "") -> 0
C61: 131.01 | D61: Horas extraordinarias | E61: 1100 | F61: 1100 | G61: =IFERROR(((F61-E61)/E61), "") -> 0
C62: 131.02 | D62: Otras remuneraciones | E62: 32200 | F62: 32200 | G62: =IFERROR(((F62-E62)/E62), "") -> 0
C63: 160.02 | D63: Cuotas Seguridad Social | E63: 43200 | F63: 43200 | G63: =IFERROR(((F63-E63)/E63), "") -> 0
B64: 1510 | E64: 571400 | F64: =SUM(F53:F63) -> 571400 | G64: =IFERROR(((F64-E64)/E64), "") -> 0
G65: =IFERROR(((F65-E65)/E65), "")
B66: 1522 | D66: URBANISMO. OFICINA GESTIÓN ARU SANTA CATALINA | E66: 2025 | F66: 2026 | G66: =IFERROR(((F66-E66)/E66), "") -> 0.00049382716
C67: 120.06 | D67: Trienios | E67: 128 | F67: 128 | G67: =IFERROR(((F67-E67)/E67), "") -> 0
C68: 131.00 | D68: Retribuciones básicas | E68: 72368 | F68: 72368 | G68: =IFERROR(((F68-E68)/E68), "") -> 0
C69: 131.01 | D69: Horas extraordinarias | E69: 0 | F69: 0 | G69: =IFERROR(((F69-E69)/E69), "")
C70: 160.02 | D70: Cuotas Seguridad Social | E70: 23000 | F70: 23000 | G70: =IFERROR(((F70-E70)/E70), "") -> 0
B71: 1522 | E71: 95496 | F71: =SUM(F67:F70) -> 95496 | G71: =IFERROR(((F71-E71)/E71), "") -> 0
G72: =IFERROR(((F72-E72)/E72), "")
B73: 1530 | D73: VÍAS PÚBLICAS URBANAS | E73: 2025 | F73: 2026 | G73: =IFERROR(((F73-E73)/E73), "") -> 0.00049382716
C74: 120.01 | D74: Sueldos del Grupo A2 | E74: 19900 | F74: 19900 | G74: =IFERROR(((F74-E74)/E74), "") -> 0
C75: 120.06 | D75: Trienios | E75: 1250 | F75: 1250 | G75: =IFERROR(((F75-E75)/E75), "") -> 0
C76: 121.00 | D76: Complemento de destino | E76: 8400 | F76: 8400 | G76: =IFERROR(((F76-E76)/E76), "") -> 0
C77: 121.01 | D77: Complemento específico | E77: 18100 | F77: 18100 | G77: =IFERROR(((F77-E77)/E77), "") -> 0
C78: 150 | D78: Productividad | E78: 900 | F78: 900 | G78: =IFERROR(((F78-E78)/E78), "") -> 0
C79: 160.00 | D79: Cuotas Seguridad Social | E79: 12500 | F79: 12500 | G79: =IFERROR(((F79-E79)/E79), "") -> 0
C80: 130.00 | D80: Retribuciones básicas | E80: 84500 | F80: 84500 | G80: =IFERROR(((F80-E80)/E80), "") -> 0
C81: 130.01 | D81: Horas extraordinarias | E81: 38500 | F81: 38500 | G81: =IFERROR(((F81-E81)/E81), "") -> 0
C82: 130.02 | D82: Otras remuneraciones | E82: 27000 | F82: 27000 | G82: =IFERROR(((F82-E82)/E82), "") -> 0
C83: 160.01 | D83: Cuotas Seguridad Social | E83: 43000 | F83: 43000 | G83: =IFERROR(((F83-E83)/E83), "") -> 0
C84: 131.00 | D84: Retribuciones básicas | E84: 230000 | F84: 230000 | G84: =IFERROR(((F84-E84)/E84), "") -> 0
C85: 131.01 | D85: Horas extraordinarias | E85: 1100 | F85: 1100 | G85: =IFERROR(((F85-E85)/E85), "") -> 0
... C87: 160.02 | D87: Cuotas Seguridad Social | E87: 80000 | F87: 80000 | G87: =IFERROR(((F87-E87)/E87), "") -> 0
B88: 1530 | E88: 605150 | F88: =SUM(F74:F87) -> 605150 | G88: =IFERROR(((F88-E88)/E88), "") -> 0
G89: =IFERROR(((F89-E89)/E89), "")
B90: 1610 | D90: ABASTECIMIENTO Y DISTRIBUCIÓN DE AGUAS | E90: 2025 | F90: 2026 | G90: =IFERROR(((F90-E90)/E90), "") -> 0.00049382716
C91: 120.01 | D91: Sueldos del Grupo A2 | E91: 20000 | F91: 20000 | G91: =IFERROR(((F91-E91)/E91), "") -> 0
C92: 120.04 | D92: Sueldos del Grupo C2 | E92: 20000 | F92: 20000 | G92: =IFERROR(((F92-E92)/E92), "") -> 0
C93: 120.06 | D93: Trienios | E93: 3800 | F93: 3800 | G93: =IFERROR(((F93-E93)/E93), "") -> 0
C94: 121.00 | D94: Complemento de destino | E94: 19050 | F94: =13000+6050 -> 19050 | G94: =IFERROR(((F94-E94)/E94), "") -> 0
C95: 121.01 | D95: Complemento específico | E95: 31800 | F95: =23000+8800 -> 31800 | G95: =IFERROR(((F95-E95)/E95), "") -> 0
C96: 150 | D96: Productividad | E96: 2250 | F96: =1600+650 -> 2250 | G96: =IFERROR(((F96-E96)/E96), "") -> 0
C97: 160.00 | D97: Cuotas Seguridad Social | E97: 18000 | F97: 18000 | G97: =IFERROR(((F97-E97)/E97), "") -> 0
C98: 130.00 | D98: Retribuciones básicas | E98: 111000 | F98: 111000 | G98: =IFERROR(((F98-E98)/E98), "") -> 0
C99: 130.01 | D99: Horas extraordinarias | E99: 31000 | F99: 31000 | G99: =IFERROR(((F99-E99)/E99), "") -> 0
C100: 130.02 | D100: Otras remuneraciones | E100: 50000 | F100: 50000 | G100: =IFERROR(((F100-E100)/E100), "") -> 0
C101: 160.01 | D101: Cuotas Seguridad Social | E101: 49000 | F101: 49000 | G101: =IFERROR(((F101-E101)/E101), "") -> 0
...

Sheet Liberaciones & Libre desig
C2: Dedic. excl. | D2: Eventuales | I2: Salario | J2: SS | K2: Ded.exc. idmn. máx | L2: TOTAL
B3: Número | C3: 4 | D3: 2 | F3: 4+3 | H3: COSTE DEDIC. EXCL | I3: =C4 * C3 -> 168000 | J3: =(C4*0.3) * C3 -> 50400 | K3: =1380 * 12 * C3 -> 66240 | L3: =SUM(I3:J3) - K3 -> 152160
B4: Coste | C4: 42000 | D4: 35000 | F4: 332320 | H4: COSTE EVENTUALES | I4: =D4 * D3 -> 70000 | J4: =(D4*0.3) * D3 -> 21000 | K4: 0 | L4: =SUM(I4:K4) -> 91000
K5: TOTAL | L5: =SUM(L3:L4) -> 243160
